libsumo/__init__.py
libsumo/_libsumo.so
libsumo/libsumo.py
libtraci/__init__.py
libtraci/_libtraci.so
libtraci/libtraci.py
libtraci-1.19.0.dist-info/METADATA
libtraci-1.19.0.dist-info/WHEEL
libtraci-1.19.0.dist-info/top_level.txt
libtraci-1.19.0.dist-info/RECORD
