Metadata-Version: 2.1
Name: libtraci
Version: 1.19.0
Summary: The python version of the libtraci API to communicate with the traffic simulation Eclipse SUMO
Home-page: https://sumo.dlr.de/docs/TraCI.html
Author: DLR and contributors
Author-email: sumo@dlr.de
License: EPL-2.0
Keywords: traffic simulation traci sumo
Classifier: Development Status :: 4 - Beta
Classifier: Intended Audience :: Developers
Classifier: Intended Audience :: Science/Research
Classifier: License :: OSI Approved :: Eclipse Public License 2.0 (EPL-2.0)
Classifier: Programming Language :: Python :: 3
Requires-Dist: traci >=1.19.0
